colify
