Metadata-Version: 1.0
Name: colify
Version: 0.0.3
Summary: Print arrays as columns
Home-page: https://github.com/looneym/colify
Author: Micheal Looney
Author-email: UNKNOWN
License: MIT
Keywords: print array column
Platform: UNKNOWN
